{
  "schemaVersion": 1,
  "name": "Giza Night",
  "tokens": {
    "Background": "#451a03",
    "Foreground": "#fde047",
    "Surface": "#713f12",
    "SurfaceForeground": "#fef9c3",
    "Primary": "#fbbf24",
    "PrimaryForeground": "#451a03",
    "Secondary": "#854d0e",
    "SecondaryForeground": "#fde047",
    "Muted": "#a16207",
    "MutedForeground": "#f59e0b",
    "Border": "#b45309",
    "Ring": "#fbbf24",
    "Success": "#4ade80",
    "SuccessForeground": "#451a03",
    "Destructive": "#f87171",
    "DestructiveForeground": "#451a03",
    "RadiusSm": "0.5rem",
    "RadiusMd": "1rem",
    "RadiusLg": "2rem",
    "FontSans": "Cinzel",
    "FontHeading": "Cinzel Decorative"
  },
  "tags": ["dark", "giza", "night", "desert"]
}
