{
  "schemaVersion": 1,
  "name": "Tidal Pool",
  "tokens": {
    "Background": "#ecfeff",
    "Foreground": "#164e63",
    "Surface": "#cffafe",
    "SurfaceForeground": "#164e63",
    "Primary": "#06b6d4",
    "PrimaryForeground": "#ffffff",
    "Secondary": "#a5f3fc",
    "SecondaryForeground": "#155e75",
    "Muted": "#67e8f9",
    "MutedForeground": "#0891b2",
    "Border": "#22d3ee",
    "Ring": "#06b6d4",
    "Success": "#22c55e",
    "SuccessForeground": "#ffffff",
    "Destructive": "#ef4444",
    "DestructiveForeground": "#ffffff",
    "RadiusSm": "0.5rem",
    "RadiusMd": "1rem",
    "RadiusLg": "2rem",
    "FontSans": "Quicksand",
    "FontHeading": "Quicksand"
  },
  "tags": ["light", "tidal", "pool", "coast"]
}
